amshan/__init__.py
amshan/aidon.py
amshan/autodecoder.py
amshan/cosem.py
amshan/fastframecheck.py
amshan/hdlc.py
amshan/kaifa.py
amshan/kamstrup.py
amshan/meter_connection.py
amshan/obis_map.py
amshan/py.typed
amshan/serial_connection_factory.py
amshan/tcp_connection_factory.py
amshan-2021.12.1.dist-info/LICENSE
amshan-2021.12.1.dist-info/METADATA
amshan-2021.12.1.dist-info/WHEEL
amshan-2021.12.1.dist-info/top_level.txt
amshan-2021.12.1.dist-info/RECORD
