Metadata-Version: 2.1
Name: amshan
Version: 2021.12.1
Summary: Decode MBUS (Meter Bus) data with special support for norwegian AMS-smart meters (HAN port)
Home-page: https://github.com/toreamun/amshan
Author: Tore Amundsen
Author-email: tore@amundsen.org
License: UNKNOWN
Keywords: meter,han,ams,mbus,aidon,kaifa,kamstrup,cosem,hdlc,fast frame check
Platform: POSIX
Platform: Windows
Classifier: Programming Language :: Python :: 3
Classifier: License :: OSI Approved :: MIT License
Classifier: Operating System :: OS Independent
Requires-Python: >=3.6
License-File: LICENSE
Requires-Dist: construct
Provides-Extra: serial
Requires-Dist: pyserial-asyncio (>=0.4) ; extra == 'serial'
